sequential_thinking/__init__.py
sequential_thinking/__main__.py
sequential_thinking/mcp_server.py
sequential_thinking/test_mcp_server.py
sequential_thinking_mcp-0.10.1.dist-info/METADATA
sequential_thinking_mcp-0.10.1.dist-info/WHEEL
sequential_thinking_mcp-0.10.1.dist-info/entry_points.txt
sequential_thinking_mcp-0.10.1.dist-info/licenses/LICENSE
sequential_thinking_mcp-0.10.1.dist-info/RECORD
