Metadata-Version: 2.4
Name: sequential-thinking-mcp
Version: 0.10.1
Summary: Sequential Thinking MCP
Project-URL: Repository, https://github.com/philogicae/sequential-thinking-mcp
Project-URL: Release, https://github.com/philogicae/sequential-thinking-mcp/releases
Project-URL: DeepWiki, https://deepwiki.com/philogicae/sequential-thinking-mcp
Author: philogicae
License-Expression: MIT
License-File: LICENSE
Requires-Python: <4.0,>=3.10
Requires-Dist: fastmcp
